[
  {
    "name": "Juan",
    "lastName": "Perez",
    "dni": 12345678,
    "country": "Argentina",
    "city": "Buenos Aires",
    "birthdate": "1990-01-01",
    "availableToWork": false,
    "email": "juan.perez@example.com",
    "password": "Asd_*1234",
    "bio": "Especialista en diagnóstico y tratamiento de enfermedades cardiovasculares. Realiza procedimientos como cateterismos y ecocardiogramas.",
    "datecreateUser": "2024-01-10"
  },
  {
    "name": "Jose Maria",
    "lastName": "Marquez",
    "dni": 12345678,
    "country": "Argentina",
    "city": "Buenos Aires",
    "birthdate": "1990-01-01",
    "availableToWork": false,
    "email": "josemaria@example.com",
    "password": "Asd_*1234",
    "bio": "Docente especializado en la enseñanza a estudiantes con necesidades educativas especiales. Desarrolla planes de estudio individualizados.",
    "datecreateUser": "2024-01-10"
  },
  {
    "name": "Maria",
    "lastName": "Gomez",
    "dni": 23456789,
    "country": "Brasil",
    "city": "Sao Paulo",
    "birthdate": "1985-05-15",
    "availableToWork": false,
    "email": "maria.gomez@example.com",
    "password": "Asd_*1234",
    "bio": "Aviador experimentado en vuelos de prueba de nuevas aeronaves. Evalúa el rendimiento y la seguridad de prototipos.",
    "datecreateUser": "2024-02-15"
  },
  {
    "name": "Carlos",
    "lastName": "Lopez",
    "dni": 34567890,
    "country": "Chile",
    "city": "Santiago",
    "birthdate": "1978-11-20",
    "availableToWork": false,
    "email": "carlos.lopez@example.com",
    "password": "Asd_*1234",
    "bio": "Experto en instalación y mantenimiento de sistemas de purificación y tratamiento de aguas residuales industriales.",
    "datecreateUser": "2024-02-20"
  },
  {
    "name": "Ana",
    "lastName": "Martinez",
    "dni": 45678901,
    "country": "Uruguay",
    "city": "Montevideo",
    "birthdate": "1992-07-30",
    "availableToWork": false,
    "email": "ana.martinez@example.com",
    "password": "Asd_*1234",
    "bio": "Especialista en corrección de malposiciones dentales y maxilares. Utiliza tecnologías avanzadas para tratamientos personalizados.",
    "datecreateUser": "2024-03-05"
  },
  {
    "name": "Pedro",
    "lastName": "Fernandez",
    "dni": 56789012,
    "country": "Paraguay",
    "city": "Asuncion",
    "birthdate": "1980-04-22",
    "availableToWork": false,
    "email": "pedro.fernandez@example.com",
    "password": "Asd_*1234",
    "bio": "Especialista en derecho penal con experiencia en litigios. Defiende a clientes en casos de delitos graves y apelaciones.",
    "datecreateUser": "2024-03-10"
  },
  {
    "name": "Lucia",
    "lastName": "Rodriguez",
    "dni": 67890123,
    "country": "Argentina",
    "city": "Rosario",
    "birthdate": "1995-03-18",
    "availableToWork": false,
    "email": "lucia.rodriguez@example.com",
    "password": "Asd_*1234",
    "bio": "Desarrollador experimentado en arquitectura de sistemas y liderazgo de equipos. Especializado en tecnologías cloud y microservicios.",
    "datecreateUser": "2024-03-15"
  },
  {
    "name": "Jorge",
    "lastName": "Gonzalez",
    "dni": 78901234,
    "country": "Brasil",
    "city": "Rio de Janeiro",
    "birthdate": "1975-09-12",
    "availableToWork": false,
    "email": "jorge.gonzalez@example.com",
    "password": "Asd_*1234",
    "bio": "Docente universitario especializado en mecánica cuántica y física de partículas. Investiga en el campo de la computación cuántica.",
    "datecreateUser": "2024-03-20"
  },
  {
    "name": "Sofia",
    "lastName": "Diaz",
    "dni": 89012345,
    "country": "Chile",
    "city": "Valparaiso",
    "birthdate": "1988-12-05",
    "availableToWork": false,
    "email": "sofia.diaz@example.com",
    "password": "Asd_*1234",
    "bio": "Líder de cocina en restaurante de alta cocina. Crea menús innovadores y gestiona un equipo de cocineros profesionales.",
    "datecreateUser": "2024-04-05"
  },
  {
    "name": "Roberto",
    "lastName": "Torres",
    "dni": 90123456,
    "country": "Uruguay",
    "city": "Punta del Este",
    "birthdate": "1983-06-17",
    "availableToWork": false,
    "email": "roberto.torres@example.com",
    "password": "Asd_*1234",
    "bio": "Profesional especializado en atención a pacientes críticos. Maneja equipos de soporte vital y administra tratamientos complejos.",
    "datecreateUser": "2024-04-10"
  },
  {
    "name": "Valentina",
    "lastName": "Silva",
    "dni": 10234567,
    "country": "Paraguay",
    "city": "Encarnacion",
    "birthdate": "1991-10-24",
    "availableToWork": false,
    "email": "valentina.silva@example.com",
    "password": "Asd_*1234",
    "bio": "Experto en detección de fraudes financieros y auditorías especiales. Colabora con agencias gubernamentales en investigaciones.",
    "datecreateUser": "2024-05-05"
  },
  {
    "name": "Martin",
    "lastName": "Mendez",
    "dni": 11234567,
    "country": "Argentina",
    "city": "Mendoza",
    "birthdate": "1987-03-14",
    "availableToWork": false,
    "email": "martin.mendez@example.com",
    "password": "Asd_*1234",
    "bio": "Especialista en mejora del rendimiento de atletas de élite. Trabaja en técnicas de concentración y manejo del estrés competitivo.",
    "datecreateUser": "2024-05-10"
  },
  {
    "name": "Laura",
    "lastName": "Morales",
    "dni": 12234567,
    "country": "Brasil",
    "city": "Salvador",
    "birthdate": "1993-08-09",
    "availableToWork": false,
    "email": "laura.morales@example.com",
    "password": "Asd_*1234",
    "bio": "Diseñador de espacios verdes urbanos y rurales. Especializado en jardines sostenibles y restauración de ecosistemas.",
    "datecreateUser": "2024-05-15"
  },
  {
    "name": "Ricardo",
    "lastName": "Romero",
    "dni": 13234567,
    "country": "Chile",
    "city": "Concepcion",
    "birthdate": "1982-11-01",
    "availableToWork": false,
    "email": "ricardo.romero@example.com",
    "password": "Asd_*1234",
    "bio": "specialista en farmacoterapia hospitalaria. Optimiza tratamientos medicamentosos y participa en ensayos clínicos.",
    "datecreateUser": "2024-06-01"
  },
  {
    "name": "Natalia",
    "lastName": "Suarez",
    "dni": 14234567,
    "country": "Uruguay",
    "city": "Colonia del Sacramento",
    "birthdate": "1976-02-25",
    "availableToWork": false,
    "email": "natalia.suarez@example.com",
    "password": "Asd_*1234",
    "bio": "Técnica certificada en mantenimiento de aeronaves comerciales. Realiza inspecciones de seguridad y reparaciones complejas.",
    "datecreateUser": "2024-06-05"
  },
  {
    "name": "Diego",
    "lastName": "Sosa",
    "dni": 15234567,
    "country": "Paraguay",
    "city": "Ciudad del Este",
    "birthdate": "1989-07-07",
    "availableToWork": false,
    "email": "diego.sosa@example.com",
    "password": "Asd_*1234",
    "bio": "Especialista en mejora del rendimiento de atletas de élite. Trabaja en técnicas de concentración y manejo del estrés competitivo",
    "datecreateUser": "2024-06-10"
  },
  {
    "name": "Isabel",
    "lastName": "Ramos",
    "dni": 16234567,
    "country": "Argentina",
    "city": "Cordoba",
    "birthdate": "1996-05-29",
    "availableToWork": false,
    "email": "isabel.ramos@example.com",
    "password": "Asd_*1234",
    "bio": "Técnico especializado en sistemas eléctricos de alta tensión. Instala y mantiene equipos en plantas industriales y centrales eléctricas",
    "datecreateUser": "2024-06-15"
  },
  {
    "name": "Francisco",
    "lastName": "Rojas",
    "dni": 17234567,
    "country": "Brasil",
    "city": "Fortaleza",
    "birthdate": "1981-10-19",
    "availableToWork": false,
    "email": "francisco.rojas@example.com",
    "password": "Asd_*1234",
    "bio": "Programador especializado en machine learning y redes neuronales. Desarrolla algoritmos para aplicaciones de IA en diversos sectores.",
    "datecreateUser": "2024-06-20"
  }
]
